MANIFEST.in
README.rst
console.py
console2.py
setup.cfg
setup.py
scalymongo/__init__.py
scalymongo/connection.py
scalymongo/cursor.py
scalymongo/document.py
scalymongo/errors.py
scalymongo/helpers.py
scalymongo/schema.py
scalymongo/schema_operators.py
scalymongo/structure_walker.py
scalymongo.egg-info/PKG-INFO
scalymongo.egg-info/SOURCES.txt
scalymongo.egg-info/dependency_links.txt
scalymongo.egg-info/entry_points.txt
scalymongo.egg-info/requires.txt
scalymongo.egg-info/top_level.txt
scalymongo.egg-info/zip-safe
scalymongo/manage/__init__.py
scalymongo/manage/ensure_indexes.py