Metadata-Version: 1.0
Name: scalymongo
Version: 0.1.6
Summary: A scaling-centric MongoDB object document mapper
Home-page: https://github.com/allancaffee/scaly-mongo
Author: Allan Caffee
Author-email: allan.caffee@gmail.com
License: BSD
Keywords: mongo sharding db
Platform: UNKNOWN
Classifier: Development Status :: 2 - Pre-Alpha
Classifier: Intended Audience :: Developers
Classifier: License :: OSI Approved :: BSD License
Classifier: Operating System :: MacOS :: MacOS X
Classifier: Operating System :: POSIX
Classifier: Programming Language :: Python
Classifier: Topic :: Database
